necst_visualizer/__init__.py
necst_visualizer/scan_check.py
necst_visualizer-0.1.1.dist-info/LICENSE
necst_visualizer-0.1.1.dist-info/WHEEL
necst_visualizer-0.1.1.dist-info/METADATA
necst_visualizer-0.1.1.dist-info/RECORD
