Metadata-Version: 2.1
Name: necst-visualizer
Version: 0.1.1
Summary: 
Home-page: https://github.com/nanten2/necst-visualizer
License: MIT
Author: FumikaDemachi
Author-email: f.demachi@a.phys.nagoya-u.ac.jp
Requires-Python: >=3.7,<3.10
Classifier: License :: OSI Approved :: MIT License
Classifier: Programming Language :: Python :: 3
Classifier: Programming Language :: Python :: 3.7
Classifier: Programming Language :: Python :: 3.8
Classifier: Programming Language :: Python :: 3.9
Requires-Dist: astropy (>=3.0,<4.0); python_version < "3.8"
Requires-Dist: astropy (>=5.0.4,<6.0.0); python_version >= "3.8"
Requires-Dist: matplotlib (>=3.4.3,<4.0.0)
Requires-Dist: n-const (>=1.0.4,<2.0.0)
Requires-Dist: neclib (>=0.7.0,<0.8.0)
Requires-Dist: necstdb (>=0.2.5,<0.3.0)
Requires-Dist: xarray (>=0.20.0,<0.21.0)
Project-URL: Repository, https://github.com/nanten2/necst-visualizer
